arduinoiot/__init__.py
ardui-0.1.dist-info/METADATA
ardui-0.1.dist-info/WHEEL
ardui-0.1.dist-info/top_level.txt
ardui-0.1.dist-info/RECORD
