Metadata-Version: 2.1
Name: ardui
Version: 0.1
Summary: package with iot codes
Author: Black_shark
